{
    "operations": [
        {
            "RIB": "18206002105487266700217",
            "Date": "28/03/2017",
            "Libelle": "Achat Auger Couturier S.A.R.L.",
            "Montant": "-140,83",
            "Devise": "Euro"
        },
        {
            "RIB": "18206002105487266700217",
            "Date": "12/04/2017",
            "Libelle": "Virement Leroux",
            "Montant": "713,49",
            "Devise": "Euro"
        },
        {
            "RIB": "18206002105487266700217",
            "Date": "12/04/2017",
            "Libelle": "Virement Baron",
            "Montant": "-576,24",
            "Devise": "Euro"
        },
        {
            "RIB": "20041100200058741005T15",
            "Date": "27/03/2017",
            "Libelle": "Virement Henry Marques S.A.S.",
            "Montant": "-445,68",
            "Devise": "Euro"
        },
        {
            "RIB": "18206002105487266700217",
            "Date": "31/03/2017",
            "Libelle": "Achat Olivier",
            "Montant": "-645,71",
            "Devise": "Euro"
        },
        {
            "RIB": "20041100200058741005T15",
            "Date": "17/03/2017",
            "Libelle": "Achat Hubert Paris et Fils",
            "Montant": "240,30",
            "Devise": "Euro"
        },
        {
            "RIB": "18206002105487266700217",
            "Date": "29/03/2017",
            "Libelle": "Achat Camus",
            "Montant": "791,83",
            "Devise": "Euro"
        },
        {
            "RIB": "20041100200058741005T15",
            "Date": "11/04/2017",
            "Libelle": "Achat Muller",
            "Montant": "598,38",
            "Devise": "Euro"
        },
        {
            "RIB": "20041100200058741005T15",
            "Date": "31/03/2017",
            "Libelle": "Service Fabre",
            "Montant": "-931,31",
            "Devise": "Euro"
        },
        {
            "RIB": "18206002105487266700217",
            "Date": "11/04/2017",
            "Libelle": "Achat Poirier S.A.S.",
            "Montant": "836,38",
            "Devise": "Euro"
        },
        {
            "RIB": "18206002105487266700217",
            "Date": "25/03/2017",
            "Libelle": "Service Le Roux",
            "Montant": "553,82",
            "Devise": "Euro"
        },
        {
            "RIB": "18206002105487266700217",
            "Date": "14/04/2017",
            "Libelle": "Achat Durand Fischer SARL",
            "Montant": "150,11",
            "Devise": "Euro"
        },
        {
            "RIB": "18206002105487266700217",
            "Date": "08/04/2017",
            "Libelle": "Service Blanchet et Fils",
            "Montant": "456,37",
            "Devise": "Euro"
        },
        {
            "RIB": "18206002105487266700217",
            "Date": "25/03/2017",
            "Libelle": "Service Schneider Guichard SARL",
            "Montant": "-17,73",
            "Devise": "Euro"
        },
        {
            "RIB": "20041100200058741005T15",
            "Date": "29/03/2017",
            "Libelle": "Service Raynaud Cousin S.A.",
            "Montant": "-941,09",
            "Devise": "Euro"
        },
        {
            "RIB": "18206002105487266700217",
            "Date": "31/03/2017",
            "Libelle": "Service Lopes SA",
            "Montant": "-99,19",
            "Devise": "Euro"
        },
        {
            "RIB": "30002005500000157845Z02",
            "Date": "12/04/2017",
            "Libelle": "Virement Dumont SARL",
            "Montant": "-610,19",
            "Devise": "Euro"
        },
        {
            "RIB": "20041100200058741005T15",
            "Date": "31/03/2017",
            "Libelle": "Virement Guyot",
            "Montant": "-690,31",
            "Devise": "Euro"
        },
        {
            "RIB": "30002005500000157845Z02",
            "Date": "22/03/2017",
            "Libelle": "Achat Mercier SARL",
            "Montant": "128,12",
            "Devise": "Euro"
        },
        {
            "RIB": "30002005500000157845Z02",
            "Date": "05/04/2017",
            "Libelle": "Achat Remy S.A.R.L.",
            "Montant": "-247,10",
            "Devise": "Euro"
        },
        {
            "RIB": "20041100200058741005T15",
            "Date": "12/04/2017",
            "Libelle": "Virement Coulon",
            "Montant": "-189,06",
            "Devise": "Euro"
        },
        {
            "RIB": "20041100200058741005T15",
            "Date": "05/04/2017",
            "Libelle": "Service Albert SA",
            "Montant": "-62,66",
            "Devise": "Euro"
        },
        {
            "RIB": "18206002105487266700217",
            "Date": "01/04/2017",
            "Libelle": "Virement Vidal",
            "Montant": "-351,39",
            "Devise": "Euro"
        },
        {
            "RIB": "30002005500000157845Z02",
            "Date": "12/04/2017",
            "Libelle": "Achat Perret",
            "Montant": "597,14",
            "Devise": "Euro"
        },
        {
            "RIB": "20041100200058741005T15",
            "Date": "07/04/2017",
            "Libelle": "Service Martin Cordier SA",
            "Montant": "-602,39",
            "Devise": "Euro"
        },
        {
            "RIB": "18206002105487266700217",
            "Date": "07/04/2017",
            "Libelle": "Achat Martel",
            "Montant": "763,37",
            "Devise": "Euro"
        },
        {
            "RIB": "20041100200058741005T15",
            "Date": "02/04/2017",
            "Libelle": "Achat Rey SA",
            "Montant": "433,03",
            "Devise": "Euro"
        },
        {
            "RIB": "18206002105487266700217",
            "Date": "04/04/2017",
            "Libelle": "Virement Bonneau",
            "Montant": "-817,55",
            "Devise": "Euro"
        },
        {
            "RIB": "30002005500000157845Z02",
            "Date": "17/03/2017",
            "Libelle": "Achat Alves",
            "Montant": "-449,86",
            "Devise": "Euro"
        },
        {
            "RIB": "18206002105487266700217",
            "Date": "17/03/2017",
            "Libelle": "Achat Maillot et Fils",
            "Montant": "-127,52",
            "Devise": "Euro"
        },
        {
            "RIB": "20041100200058741005T15",
            "Date": "12/04/2017",
            "Libelle": "Achat Rousseau",
            "Montant": "-980,14",
            "Devise": "Euro"
        },
        {
            "RIB": "30002005500000157845Z02",
            "Date": "12/04/2017",
            "Libelle": "Achat Bodin",
            "Montant": "-971,62",
            "Devise": "Euro"
        },
        {
            "RIB": "30002005500000157845Z02",
            "Date": "04/04/2017",
            "Libelle": "Achat Pelletier Leleu SA",
            "Montant": "375,94",
            "Devise": "Euro"
        },
        {
            "RIB": "18206002105487266700217",
            "Date": "07/04/2017",
            "Libelle": "Achat Perrier",
            "Montant": "649,35",
            "Devise": "Euro"
        },
        {
            "RIB": "20041100200058741005T15",
            "Date": "15/03/2017",
            "Libelle": "Service Paul Gregoire S.A.S.",
            "Montant": "775,59",
            "Devise": "Euro"
        },
        {
            "RIB": "30002005500000157845Z02",
            "Date": "31/03/2017",
            "Libelle": "Achat Guyot Potier S.A.S.",
            "Montant": "398,04",
            "Devise": "Euro"
        },
        {
            "RIB": "20041100200058741005T15",
            "Date": "16/03/2017",
            "Libelle": "Service Leclercq",
            "Montant": "721,22",
            "Devise": "Euro"
        },
        {
            "RIB": "20041100200058741005T15",
            "Date": "02/04/2017",
            "Libelle": "Achat Munoz Coulon SARL",
            "Montant": "-699,21",
            "Devise": "Euro"
        },
        {
            "RIB": "18206002105487266700217",
            "Date": "09/04/2017",
            "Libelle": "Service Denis Bazin SA",
            "Montant": "310,62",
            "Devise": "Euro"
        },
        {
            "RIB": "20041100200058741005T15",
            "Date": "12/04/2017",
            "Libelle": "Virement Denis et Fils",
            "Montant": "590,65",
            "Devise": "Euro"
        },
        {
            "RIB": "30002005500000157845Z02",
            "Date": "10/04/2017",
            "Libelle": "Achat Leroux",
            "Montant": "882,77",
            "Devise": "Euro"
        },
        {
            "RIB": "30002005500000157845Z02",
            "Date": "12/04/2017",
            "Libelle": "Virement Boutin Besnard et Fils",
            "Montant": "-174,47",
            "Devise": "Euro"
        },
        {
            "RIB": "30002005500000157845Z02",
            "Date": "13/04/2017",
            "Libelle": "Virement Chauveau",
            "Montant": "-779,83",
            "Devise": "Euro"
        },
        {
            "RIB": "20041100200058741005T15",
            "Date": "28/03/2017",
            "Libelle": "Service Hoareau SA",
            "Montant": "-999,40",
            "Devise": "Euro"
        },
        {
            "RIB": "30002005500000157845Z02",
            "Date": "20/03/2017",
            "Libelle": "Virement Wagner SA",
            "Montant": "-251,42",
            "Devise": "Euro"
        },
        {
            "RIB": "18206002105487266700217",
            "Date": "19/03/2017",
            "Libelle": "Achat Raynaud Renaud et Fils",
            "Montant": "-915,08",
            "Devise": "Euro"
        },
        {
            "RIB": "20041100200058741005T15",
            "Date": "13/04/2017",
            "Libelle": "Achat Toussaint",
            "Montant": "-977,27",
            "Devise": "Euro"
        },
        {
            "RIB": "18206002105487266700217",
            "Date": "04/04/2017",
            "Libelle": "Achat Merle",
            "Montant": "-116,16",
            "Devise": "Euro"
        },
        {
            "RIB": "20041100200058741005T15",
            "Date": "06/04/2017",
            "Libelle": "Achat Remy Gilles SARL",
            "Montant": "911,22",
            "Devise": "Euro"
        },
        {
            "RIB": "30002005500000157845Z02",
            "Date": "16/03/2017",
            "Libelle": "Virement De Oliveira",
            "Montant": "-444,29",
            "Devise": "Euro"
        },
        {
            "RIB": "20041100200058741005T15",
            "Date": "02/04/2017",
            "Libelle": "Virement Masse SA",
            "Montant": "338,23",
            "Devise": "Euro"
        },
        {
            "RIB": "30002005500000157845Z02",
            "Date": "13/04/2017",
            "Libelle": "Service Delmas Torres et Fils",
            "Montant": "-4,60",
            "Devise": "Euro"
        },
        {
            "RIB": "20041100200058741005T15",
            "Date": "07/04/2017",
            "Libelle": "Service Petitjean SA",
            "Montant": "524,11",
            "Devise": "Euro"
        },
        {
            "RIB": "30002005500000157845Z02",
            "Date": "16/03/2017",
            "Libelle": "Virement Martineau S.A.R.L.",
            "Montant": "-484,81",
            "Devise": "Euro"
        },
        {
            "RIB": "20041100200058741005T15",
            "Date": "26/03/2017",
            "Libelle": "Service Paris",
            "Montant": "912,84",
            "Devise": "Euro"
        },
        {
            "RIB": "20041100200058741005T15",
            "Date": "29/03/2017",
            "Libelle": "Service Rodrigues",
            "Montant": "-585,11",
            "Devise": "Euro"
        },
        {
            "RIB": "18206002105487266700217",
            "Date": "31/03/2017",
            "Libelle": "Achat Collin",
            "Montant": "-201,96",
            "Devise": "Euro"
        },
        {
            "RIB": "30002005500000157845Z02",
            "Date": "06/04/2017",
            "Libelle": "Achat Cousin",
            "Montant": "272,42",
            "Devise": "Euro"
        },
        {
            "RIB": "20041100200058741005T15",
            "Date": "10/04/2017",
            "Libelle": "Virement Gay S.A.S.",
            "Montant": "-608,41",
            "Devise": "Euro"
        },
        {
            "RIB": "20041100200058741005T15",
            "Date": "02/04/2017",
            "Libelle": "Achat Gilles Marty S.A.S.",
            "Montant": "-636,22",
            "Devise": "Euro"
        },
        {
            "RIB": "30002005500000157845Z02",
            "Date": "05/04/2017",
            "Libelle": "Virement Morvan S.A.R.L.",
            "Montant": "682,90",
            "Devise": "Euro"
        },
        {
            "RIB": "20041100200058741005T15",
            "Date": "12/04/2017",
            "Libelle": "Virement Pereira SARL",
            "Montant": "789,69",
            "Devise": "Euro"
        },
        {
            "RIB": "20041100200058741005T15",
            "Date": "27/03/2017",
            "Libelle": "Virement Fournier",
            "Montant": "-445,97",
            "Devise": "Euro"
        },
        {
            "RIB": "30002005500000157845Z02",
            "Date": "11/04/2017",
            "Libelle": "Service Roux",
            "Montant": "448,29",
            "Devise": "Euro"
        },
        {
            "RIB": "18206002105487266700217",
            "Date": "28/03/2017",
            "Libelle": "Virement Blanc",
            "Montant": "-44,92",
            "Devise": "Euro"
        },
        {
            "RIB": "30002005500000157845Z02",
            "Date": "01/04/2017",
            "Libelle": "Achat Gregoire Allain SARL",
            "Montant": "277,63",
            "Devise": "Euro"
        },
        {
            "RIB": "18206002105487266700217",
            "Date": "29/03/2017",
            "Libelle": "Service Faivre",
            "Montant": "-169,41",
            "Devise": "Euro"
        },
        {
            "RIB": "20041100200058741005T15",
            "Date": "25/03/2017",
            "Libelle": "Virement Chevalier",
            "Montant": "-476,44",
            "Devise": "Euro"
        },
        {
            "RIB": "20041100200058741005T15",
            "Date": "24/03/2017",
            "Libelle": "Service Delattre SARL",
            "Montant": "191,06",
            "Devise": "Euro"
        },
        {
            "RIB": "18206002105487266700217",
            "Date": "01/04/2017",
            "Libelle": "Achat Faure S.A.R.L.",
            "Montant": "-938,74",
            "Devise": "Euro"
        },
        {
            "RIB": "30002005500000157845Z02",
            "Date": "19/03/2017",
            "Libelle": "Service Guillet Laine SA",
            "Montant": "98,41",
            "Devise": "Euro"
        },
        {
            "RIB": "20041100200058741005T15",
            "Date": "31/03/2017",
            "Libelle": "Service Dumont SA",
            "Montant": "622,91",
            "Devise": "Euro"
        },
        {
            "RIB": "20041100200058741005T15",
            "Date": "22/03/2017",
            "Libelle": "Service Martinez",
            "Montant": "923,88",
            "Devise": "Euro"
        },
        {
            "RIB": "18206002105487266700217",
            "Date": "03/04/2017",
            "Libelle": "Virement Blanchard et Fils",
            "Montant": "-26,99",
            "Devise": "Euro"
        },
        {
            "RIB": "18206002105487266700217",
            "Date": "16/03/2017",
            "Libelle": "Achat Vidal Bailly S.A.",
            "Montant": "-478,68",
            "Devise": "Euro"
        },
        {
            "RIB": "30002005500000157845Z02",
            "Date": "31/03/2017",
            "Libelle": "Virement Guichard S.A.R.L.",
            "Montant": "-389,73",
            "Devise": "Euro"
        },
        {
            "RIB": "18206002105487266700217",
            "Date": "03/04/2017",
            "Libelle": "Achat Ollivier S.A.",
            "Montant": "-596,66",
            "Devise": "Euro"
        },
        {
            "RIB": "30002005500000157845Z02",
            "Date": "29/03/2017",
            "Libelle": "Achat Dupont",
            "Montant": "195,63",
            "Devise": "Euro"
        },
        {
            "RIB": "20041100200058741005T15",
            "Date": "28/03/2017",
            "Libelle": "Service Hernandez",
            "Montant": "-956,70",
            "Devise": "Euro"
        },
        {
            "RIB": "30002005500000157845Z02",
            "Date": "26/03/2017",
            "Libelle": "Achat Colin SA",
            "Montant": "-677,92",
            "Devise": "Euro"
        },
        {
            "RIB": "18206002105487266700217",
            "Date": "04/04/2017",
            "Libelle": "Service Bourgeois",
            "Montant": "486,89",
            "Devise": "Euro"
        },
        {
            "RIB": "30002005500000157845Z02",
            "Date": "10/04/2017",
            "Libelle": "Virement Guichard",
            "Montant": "-826,46",
            "Devise": "Euro"
        },
        {
            "RIB": "18206002105487266700217",
            "Date": "21/03/2017",
            "Libelle": "Achat Payet",
            "Montant": "486,79",
            "Devise": "Euro"
        },
        {
            "RIB": "18206002105487266700217",
            "Date": "27/03/2017",
            "Libelle": "Service Perez",
            "Montant": "208,07",
            "Devise": "Euro"
        },
        {
            "RIB": "30002005500000157845Z02",
            "Date": "04/04/2017",
            "Libelle": "Virement Blanc Bruneau S.A.",
            "Montant": "-298,75",
            "Devise": "Euro"
        },
        {
            "RIB": "20041100200058741005T15",
            "Date": "04/04/2017",
            "Libelle": "Achat Vincent et Fils",
            "Montant": "869,11",
            "Devise": "Euro"
        },
        {
            "RIB": "18206002105487266700217",
            "Date": "15/03/2017",
            "Libelle": "Service Klein Leclerc et Fils",
            "Montant": "-283,20",
            "Devise": "Euro"
        },
        {
            "RIB": "30002005500000157845Z02",
            "Date": "29/03/2017",
            "Libelle": "Achat Dumont",
            "Montant": "660,92",
            "Devise": "Euro"
        },
        {
            "RIB": "20041100200058741005T15",
            "Date": "22/03/2017",
            "Libelle": "Achat Ollivier",
            "Montant": "32,23",
            "Devise": "Euro"
        },
        {
            "RIB": "30002005500000157845Z02",
            "Date": "20/03/2017",
            "Libelle": "Virement Clement Auger SA",
            "Montant": "-485,78",
            "Devise": "Euro"
        },
        {
            "RIB": "18206002105487266700217",
            "Date": "03/04/2017",
            "Libelle": "Achat Laporte S.A.",
            "Montant": "-840,22",
            "Devise": "Euro"
        },
        {
            "RIB": "30002005500000157845Z02",
            "Date": "10/04/2017",
            "Libelle": "Service Fontaine SA",
            "Montant": "-803,83",
            "Devise": "Euro"
        },
        {
            "RIB": "18206002105487266700217",
            "Date": "12/04/2017",
            "Libelle": "Virement Jacques",
            "Montant": "373,02",
            "Devise": "Euro"
        },
        {
            "RIB": "18206002105487266700217",
            "Date": "19/03/2017",
            "Libelle": "Service Bousquet Le Roux S.A.",
            "Montant": "826,03",
            "Devise": "Euro"
        },
        {
            "RIB": "20041100200058741005T15",
            "Date": "06/04/2017",
            "Libelle": "Virement Marty",
            "Montant": "-985,45",
            "Devise": "Euro"
        },
        {
            "RIB": "18206002105487266700217",
            "Date": "18/03/2017",
            "Libelle": "Virement Breton Blanchard SARL",
            "Montant": "445,04",
            "Devise": "Euro"
        },
        {
            "RIB": "20041100200058741005T15",
            "Date": "19/03/2017",
            "Libelle": "Virement Foucher",
            "Montant": "911,89",
            "Devise": "Euro"
        },
        {
            "RIB": "20041100200058741005T15",
            "Date": "02/04/2017",
            "Libelle": "Virement Vallet",
            "Montant": "413,07",
            "Devise": "Euro"
        },
        {
            "RIB": "30002005500000157845Z02",
            "Date": "17/03/2017",
            "Libelle": "Achat Da Silva Colas S.A.S.",
            "Montant": "735,56",
            "Devise": "Euro"
        },
        {
            "RIB": "30002005500000157845Z02",
            "Date": "11/04/2017",
            "Libelle": "Virement Gaudin",
            "Montant": "-400,45",
            "Devise": "Euro"
        }
    ]
}
